odoo/addons/mail_no_autofollow/LICENSE
odoo/addons/mail_no_autofollow/README.rst
odoo/addons/mail_no_autofollow/__init__.py
odoo/addons/mail_no_autofollow/__manifest__.py
odoo/addons/mail_no_autofollow/images/screen.png
odoo/addons/mail_no_autofollow/models/__init__.py
odoo/addons/mail_no_autofollow/models/mail_thread.py
odoo/addons/mail_no_autofollow/static/description/icon.png
odoo/addons/mail_no_autofollow/static/description/index.html
odoo/addons/mail_no_autofollow/tests/TEST_INSTRUCTIONS.rst
odoo_addon_mail_no_autofollow-18.0.1.0.0.dist-info/METADATA
odoo_addon_mail_no_autofollow-18.0.1.0.0.dist-info/WHEEL
odoo_addon_mail_no_autofollow-18.0.1.0.0.dist-info/top_level.txt
odoo_addon_mail_no_autofollow-18.0.1.0.0.dist-info/RECORD
